edutools_moodle/__init__.py
edutools_moodle/api.py
edutools_moodle/assignments.py
edutools_moodle/base.py
edutools_moodle/grades.py
edutools_moodle/groups.py
edutools_moodle/py.typed
edutools_moodle/test.py
edutools_moodle/users.py
edutools_moodle-0.2.1.dist-info/licenses/LICENSE
tests/__init__.py
tests/conftest.py
tests/test_api.py
tests/test_assignments.py
tests/test_grades.py
tests/test_groups.py
tests/test_users.py
edutools_moodle-0.2.1.dist-info/METADATA
edutools_moodle-0.2.1.dist-info/WHEEL
edutools_moodle-0.2.1.dist-info/top_level.txt
edutools_moodle-0.2.1.dist-info/RECORD
