Metadata-Version: 2.4
Name: edutools-moodle
Version: 0.2.1
Summary: Python package for Moodle API interactions in educational contexts
Home-page: https://github.com/najasoft/edutools-moodle
Author: Nadiri Abdeljalil
Author-email: nadiri@najasoft.com
Classifier: Development Status :: 3 - Alpha
Classifier: Intended Audience :: Education
Classifier: License :: OSI Approved :: MIT License
Classifier: Programming Language :: Python :: 3
Classifier: Programming Language :: Python :: 3.8
Classifier: Programming Language :: Python :: 3.9
Classifier: Programming Language :: Python :: 3.10
Classifier: Programming Language :: Python :: 3.11
Classifier: Programming Language :: Python :: 3.12
Requires-Python: >=3.8
License-File: LICENSE
Requires-Dist: requests>=2.28.0
Dynamic: author
Dynamic: author-email
Dynamic: classifier
Dynamic: description
Dynamic: description-content-type
Dynamic: home-page
Dynamic: license-file
Dynamic: requires-dist
Dynamic: requires-python
Dynamic: summary
